{
  "id": "eyewear-item-dailies",
  "name": "ClearVue DayFresh — 30 pack",
  "description": "ClearVue DayFresh daily disposable contact lenses. Water gradient technology for all-day comfort. Box of 30 lenses.",
  "type": "STOCK",
  "status": "ACTIVE",
  "salesUnitOfMeasurement": "EA",
  "referencePriceUnitOfMeasurement": "EA",
  "referencePriceConversionFactor": 1.0,
  "assortmentType": "IN_ASSORTMENT",
  "businessUnitGroupId": "eyewear-bug-001",
  "brand": "ClearVue",
  "itemCategoryId": "eyewear-cat-frames-001",
  "additionalProperties": [
    { "id": "pack_quantity", "name": "Pack Quantity", "value": "30", "dataType": "STRING", "isMandatory": false },
    { "id": "lens_type", "name": "Lens Type", "value": "Daily Disposable", "dataType": "STRING", "isMandatory": false },
    { "id": "material", "name": "Material", "value": "Delefilcon A", "dataType": "STRING", "isMandatory": false }
  ]
}
